libsubmit/__init__.py
libsubmit/error.py
libsubmit/utils.py
libsubmit/version.py
libsubmit/channels/__init__.py
libsubmit/channels/channel_base.py
libsubmit/channels/errors.py
libsubmit/channels/local/__init__.py
libsubmit/channels/local/local.py
libsubmit/channels/ssh/__init__.py
libsubmit/channels/ssh/ssh.py
libsubmit/channels/ssh_il/__init__.py
libsubmit/channels/ssh_il/ssh_il.py
libsubmit/launchers/__init__.py
libsubmit/launchers/launchers.py
libsubmit/providers/__init__.py
libsubmit/providers/cluster_provider.py
libsubmit/providers/provider_base.py
libsubmit/providers/aws/__init__.py
libsubmit/providers/aws/aws.py
libsubmit/providers/aws/template.py
libsubmit/providers/azure/__init__.py
libsubmit/providers/azure/azure.py
libsubmit/providers/azure/deployer.py
libsubmit/providers/cobalt/__init__.py
libsubmit/providers/cobalt/cobalt.py
libsubmit/providers/cobalt/template.py
libsubmit/providers/condor/__init__.py
libsubmit/providers/condor/condor.py
libsubmit/providers/condor/template.py
libsubmit/providers/googlecloud/__init__.py
libsubmit/providers/googlecloud/googlecloud.py
libsubmit/providers/grid_engine/__init__.py
libsubmit/providers/grid_engine/grid_engine.py
libsubmit/providers/grid_engine/template.py
libsubmit/providers/jetstream/__init__.py
libsubmit/providers/jetstream/jetstream.py
libsubmit/providers/kubernetes/__init__.py
libsubmit/providers/kubernetes/kube.py
libsubmit/providers/kubernetes/template.py
libsubmit/providers/local/__init__.py
libsubmit/providers/local/local.py
libsubmit/providers/slurm/__init__.py
libsubmit/providers/slurm/slurm.py
libsubmit/providers/slurm/template.py
libsubmit/providers/torque/__init__.py
libsubmit/providers/torque/template.py
libsubmit/providers/torque/torque.py
libsubmit-0.5.0.dist-info/DESCRIPTION.rst
libsubmit-0.5.0.dist-info/METADATA
libsubmit-0.5.0.dist-info/RECORD
libsubmit-0.5.0.dist-info/WHEEL
libsubmit-0.5.0.dist-info/metadata.json
libsubmit-0.5.0.dist-info/top_level.txt
